ouroboros/__init__.py
ouroboros/ouroboros.py
ouroboros_gis-1.0.8.dist-info/METADATA
ouroboros_gis-1.0.8.dist-info/WHEEL
ouroboros_gis-1.0.8.dist-info/licenses/LICENSE
ouroboros_gis-1.0.8.dist-info/RECORD
