Metadata-Version: 2.4
Name: ouroboros-gis
Version: 1.0.8
Summary: Towards more pythonic use of GeoDatabases
Project-URL: homepage, https://pypi.org/project/ouroboros-gis/
Project-URL: documentation, https://ouroboros-gis.readthedocs.io/en/latest/
Project-URL: repository, https://github.com/corbel-spatial/ouroboros
Project-URL: issues, https://github.com/corbel-spatial/ouroboros/issues
Project-URL: changelog, https://github.com/corbel-spatial/ouroboros/blob/main/CHANGELOG.md
Author-email: Peter Von der Porten <dev@corbelspatial.com>
License-Expression: MIT
License-File: LICENSE
Classifier: Development Status :: 4 - Beta
Classifier: Intended Audience :: Information Technology
Classifier: Operating System :: MacOS
Classifier: Operating System :: Microsoft :: Windows :: Windows 10
Classifier: Operating System :: Microsoft :: Windows :: Windows 11
Classifier: Operating System :: OS Independent
Classifier: Operating System :: POSIX :: Linux
Classifier: Programming Language :: Python :: 3.10
Classifier: Programming Language :: Python :: 3.11
Classifier: Programming Language :: Python :: 3.12
Classifier: Programming Language :: Python :: 3.13
Classifier: Programming Language :: Python :: 3.14
Classifier: Topic :: Scientific/Engineering :: GIS
Requires-Python: >=3.10
Requires-Dist: geojson
Requires-Dist: geopandas>=1.1.0
Requires-Dist: matplotlib>=3.10.0
Requires-Dist: pyarrow
Requires-Dist: xmltodict>=1.0.0
Provides-Extra: raster
Requires-Dist: gdal>=3.8; extra == 'raster'
